pegwords
